		{
			"key": "javascript",
			"name": "SonarJS",
			"filename": "sonar-javascript-plugin-4.1.0.6085.jar",
			"sonarLintSupported": true,
			"hash": "132aaa5c3a6da2c09af83d327b1fc182",
			"updatedAt": 1520315802623,
			"description": "Code Analyzer for JavaScript",
			"version": "4.1 (build 6085)",
			"license": "GNU LGPL 3",
			"organizationName": "SonarSource and Eriks Nukis",
			"editionBundled": false,
			"homepageUrl": "http://redirect.sonarsource.com/plugins/javascript.html",
			"issueTrackerUrl": "https://github.com/SonarSource/sonar-javascript/issues",
			"implementationBuild": "0a33c1a749126986ce73dd749f64f14ff4c91e33"
		}